midterm/src/datapath.v
module datapath(
    input wire clk,
    input wire rst,
    input wire [1:0] sel,
    output reg [1:0] S,
    output reg [3:0] LED
);

    wire [1:0] I0;
    wire [1:0] I1;
    wire [1:0] I2;
    reg [1:0] next_S;

    assign I0 = S; // hold path
    assign I1 = S + 2'd1; // +1 path，2-bit 會自己繞回 00
    assign I2 = S - 2'd1; // -1 path，00 往下會變 11

    // 這裡就是 (c) 圖上的 3-to-1 MUX
    always @(*) begin
        case (sel)
            2'b00: next_S = I0;
            2'b01: next_S = I1;
            2'b10: next_S = I2;
            default: next_S = I0;
        endcase
    end

    // state register，存現在的 S
    always @(posedge clk or posedge rst) begin
        if (rst) begin
            S <= 2'b00;
        end else begin
            S <= next_S;
        end
    end

    // decoder，S 對應到哪顆 LED 亮
    always @(*) begin
        case (S)
            2'b00: LED = 4'b0001;
            2'b01: LED = 4'b0010;
            2'b10: LED = 4'b0100;
            2'b11: LED = 4'b1000;
            default: LED = 4'b0001;
        endcase
    end

endmodule

midterm/src/controller_fsm.v
module controller_fsm(
    input wire [1:0] S, // 從 datapath 回來的目前 state
    input wire go, // go=1 才會跑，go=0 就 hold
    input wire M, // M=1 往上，M=0 往下
    output reg [1:0] sel // 拿來選 MUX 要走哪一條路
);

    // sel=00 選 hold，sel=01 選 +1，sel=10 選 -1
    always @(*) begin
        if (go == 1'b0) begin
            sel = 2'b00; // go 關掉就維持 S
        end else begin
            if (M == 1'b1) begin
                sel = 2'b01; // 往上數
            end else begin
                sel = 2'b10; // 往下數
            end
        end
    end

endmodule

midterm/src/top_controller.v
module top_controller(
    input wire clk,
    input wire rst,
    input wire go,
    input wire M,
    output wire [1:0] S,
    output wire [3:0] LED,
    output wire [1:0] sel
);

    // 這個 top 只是把 controller 跟 datapath 接起來
    controller_fsm u_controller (
        .S(S),
        .go(go),
        .M(M),
        .sel(sel)
    );

    datapath u_datapath (
        .clk(clk),
        .rst(rst),
        .sel(sel),
        .S(S),
        .LED(LED)
    );

endmodule

midterm/src/tb_top_controller.v
`timescale 1ns/1ps

module tb_top_controller;

    reg clk;
    reg rst;
    reg go;
    reg M;

    wire [1:0] S;
    wire [3:0] LED;
    wire [1:0] sel;

    top_controller uut (
        .clk(clk),
        .rst(rst),
        .go(go),
        .M(M),
        .S(S),
        .LED(LED),
        .sel(sel)
    );

    always #5 clk = ~clk; // clock 10ns 變一次週期

    initial begin
        $dumpfile("midterm_controller.vcd");
        $dumpvars(0, tb_top_controller);

        clk = 0;
        rst = 1;
        go = 0;
        M = 0;

        #10;
        rst = 0; // reset 完就讓電路開始正常跑

        go = 0;
        M = 0;
        #30; // case: hold

        go = 0;
        M = 1;
        #30; // case: 還是 hold，因為 go=0

        go = 1;
        M = 1;
        #60; // case: count up

        go = 0;
        M = 1;
        #30; // case: 中間停一下

        go = 1;
        M = 0;
        #60; // case: count down

        go = 0;
        M = 0;
        #30; // case: 最後再 hold

        $finish;
    end

    initial begin
        $monitor("time=%0t | rst=%b go=%b M=%b sel=%b S=%b LED=%b",
                 $time, rst, go, M, sel, S, LED);
    end

endmodule

midterm/src/midterm_controller.vcd
$date
	Sun Apr 26 16:13:27 2026
$end
$version
	Icarus Verilog
$end
$timescale
	1ps
$end
$scope module tb_top_controller $end
$var wire 2 ! sel [1:0] $end
$var wire 2 " S [1:0] $end
$var wire 4 # LED [3:0] $end
$var reg 1 $ M $end
$var reg 1 % clk $end
$var reg 1 & go $end
$var reg 1 ' rst $end
$scope module uut $end
$var wire 1 $ M $end
$var wire 1 % clk $end
$var wire 1 & go $end
$var wire 1 ' rst $end
$var wire 2 ( sel [1:0] $end
$var wire 2 ) S [1:0] $end
$var wire 4 * LED [3:0] $end
$scope module u_controller $end
$var wire 1 $ M $end
$var wire 1 & go $end
$var wire 2 + S [1:0] $end
$var reg 2 , sel [1:0] $end
$upscope $end
$scope module u_datapath $end
$var wire 2 - I0 [1:0] $end
$var wire 1 % clk $end
$var wire 1 ' rst $end
$var wire 2 . sel [1:0] $end
$var wire 2 / I2 [1:0] $end
$var wire 2 0 I1 [1:0] $end
$var reg 4 1 LED [3:0] $end
$var reg 2 2 S [1:0] $end
$var reg 2 3 next_S [1:0] $end
$upscope $end
$upscope $end
$upscope $end
$enddefinitions $end
$comment Show the parameter values. $end
$dumpall
$end
#0
$dumpvars
b0 3
b0 2
b1 1
b1 0
b11 /
b0 .
b0 -
b0 ,
b0 +
b1 *
b0 )
b0 (
1'
0&
0%
0$
b1 #
b0 "
b0 !
$end
#5000
1%
#10000
0%
0'
#15000
1%
#20000
0%
#25000
1%
#30000
0%
#35000
1%
#40000
0%
1$
#45000
1%
#50000
0%
#55000
1%
#60000
0%
#65000
1%
#70000
b1 3
b1 !
b1 (
b1 ,
b1 .
0%
1&
#75000
b10 3
b10 #
b10 *
b10 1
b10 0
b0 /
b1 -
b1 "
b1 )
b1 +
b1 2
1%
#80000
0%
#85000
b11 3
b100 #
b100 *
b100 1
b11 0
b1 /
b10 -
b10 "
b10 )
b10 +
b10 2
1%
#90000
0%
#95000
b0 3
b1000 #
b1000 *
b1000 1
b0 0
b10 /
b11 -
b11 "
b11 )
b11 +
b11 2
1%
#100000
0%
#105000
b1 3
b1 #
b1 *
b1 1
b1 0
b11 /
b0 -
b0 "
b0 )
b0 +
b0 2
1%
#110000
0%
#115000
b10 3
b10 #
b10 *
b10 1
b10 0
b0 /
b1 -
b1 "
b1 )
b1 +
b1 2
1%
#120000
0%
#125000
b11 3
b100 #
b100 *
b100 1
b11 0
b1 /
b10 -
b10 "
b10 )
b10 +
b10 2
1%
#130000
b10 3
b0 !
b0 (
b0 ,
b0 .
0%
0&
#135000
1%
#140000
0%
#145000
1%
#150000
0%
#155000
1%
#160000
b1 3
b10 !
b10 (
b10 ,
b10 .
0%
0$
1&
#165000
b0 3
b10 #
b10 *
b10 1
b10 0
b0 /
b1 -
b1 "
b1 )
b1 +
b1 2
1%
#170000
0%
#175000
b11 3
b1 #
b1 *
b1 1
b1 0
b11 /
b0 -
b0 "
b0 )
b0 +
b0 2
1%
#180000
0%
#185000
b10 3
b1000 #
b1000 *
b1000 1
b0 0
b10 /
b11 -
b11 "
b11 )
b11 +
b11 2
1%
#190000
0%
#195000
b1 3
b100 #
b100 *
b100 1
b11 0
b1 /
b10 -
b10 "
b10 )
b10 +
b10 2
1%
#200000
0%
#205000
b0 3
b10 #
b10 *
b10 1
b10 0
b0 /
b1 -
b1 "
b1 )
b1 +
b1 2
1%
#210000
0%
#215000
b11 3
b1 #
b1 *
b1 1
b1 0
b11 /
b0 -
b0 "
b0 )
b0 +
b0 2
1%
#220000
b0 3
b0 !
b0 (
b0 ,
b0 .
0%
0&
